[
    {
        "name": "Wine - Hardys Bankside Shiraz",
        "description": "Inanun ge fifg dtsj lctizl s zzcm f tdqbrv jluvfbg.",
        "price": 383.21,
        "averageRating": 1.4
    },
    {
        "name": "Food Colouring - Red",
        "description": "Wmgfhd fz sgym gkde fjpddy y gkqc z qfdibr wjfnwks.",
        "price": 222.06,
        "averageRating": 2.0
    },
    {
        "name": "Pork Casing",
        "description": "Irugpr sb emks vbxb ssygcn c dvbn d lhekaa ollaxtc.",
        "price": 354.63,
        "averageRating": 4.2
    },
    {
        "name": "Lemonade - Island Tea, 591 Ml",
        "description": "Jrxsss kj vftx uqdp blypna f bari m txzstm vosdbed.",
        "price": 387.41,
        "averageRating": 3.9
    },
    {
        "name": "Cheese - Fontina",
        "description": "Rdcwkn hj fuug kpcg abzami r qomr v acyncd bltevwu.",
        "price": 148.4,
        "averageRating": 4.2
    },
    {
        "name": "Salmon - Canned",
        "description": "Nhhlmn su elcv oscq mppyed s yxgl m ffycnv dbjvzah.",
        "price": 34.71,
        "averageRating": 2.4
    },
    {
        "name": "Pasta - Bauletti, Chicken White",
        "description": "Muhyjd gd fbpz vlet iqcgce l aigs n rvporh itvrdjb.",
        "price": 420.09,
        "averageRating": 2.5
    },
    {
        "name": "The Pop Shoppe - Black Cherry",
        "description": "Erjhay oi hiiz aqcx vendyp x spzu t ukzzvj fasqxxk.",
        "price": 22.51,
        "averageRating": 1.3
    },
    {
        "name": "Lemon Pepper",
        "description": "Wmydry mo jkay pajx nurjet i ygmr b nqqqrp wsuchst.",
        "price": 18.14,
        "averageRating": 1.9
    },
    {
        "name": "Sauce - White, Mix",
        "description": "Ookmys pk nnbf geyh ttskog u thsz o wlxlgx riyjfcc.",
        "price": 137.41,
        "averageRating": 4.6
    }
]
